setup.py
txt2Excel.egg-info/PKG-INFO
txt2Excel.egg-info/SOURCES.txt
txt2Excel.egg-info/dependency_links.txt
txt2Excel.egg-info/top_level.txt
txt2excel/__init__.py
txt2excel/configGEN.py
txt2excel/readtxt.py