Metadata-Version: 1.0
Name: txt2Excel
Version: 0.0.1
Summary: a library for coretek Developer
Home-page: UNKNOWN
Author: Pope
Author-email: Mcpylon@gmail.com
License: MIT License
Keywords: txt excel
Platform: any
